ixnetrestwrap/ClassInheritance.py
ixnetrestwrap/IxNetRestApi.py
ixnetrestwrap/IxNetRestApiClassicProtocol.py
ixnetrestwrap/IxNetRestApiFileMgmt.py
ixnetrestwrap/IxNetRestApiGlobals.py
ixnetrestwrap/IxNetRestApiPacketCapture.py
ixnetrestwrap/IxNetRestApiPortMgmt.py
ixnetrestwrap/IxNetRestApiProtocol.py
ixnetrestwrap/IxNetRestApiQuickTest.py
ixnetrestwrap/IxNetRestApiStatistics.py
ixnetrestwrap/IxNetRestApiTraffic.py
ixnetrestwrap/__init__.py
ixnetrestwrap-0.0.11.dist-info/DESCRIPTION.rst
ixnetrestwrap-0.0.11.dist-info/METADATA
ixnetrestwrap-0.0.11.dist-info/RECORD
ixnetrestwrap-0.0.11.dist-info/WHEEL
ixnetrestwrap-0.0.11.dist-info/metadata.json
ixnetrestwrap-0.0.11.dist-info/top_level.txt
