Metadata-Version: 2.0
Name: ixnetrestwrap
Version: 0.0.11
Summary: Rest API Wrapper For IxNetwork
Home-page: https://github.com/ParthibanRamachandran/IxNetwork/tree/master/RestApi/Python/Modules
Author: Parthiban Ramachandran
Author-email: rparthibaan@gmail.com
License: UNKNOWN
Platform: UNKNOWN
Classifier: Programming Language :: Python :: 3
Classifier: License :: OSI Approved :: MIT License
Classifier: Operating System :: OS Independent
